replit/storage/__init__.py
replit/storage/client.py
replit/storage/config.py
replit/storage/errors.py
replit_storage-0.0.1a3.dist-info/METADATA
replit_storage-0.0.1a3.dist-info/WHEEL
replit_storage-0.0.1a3.dist-info/RECORD
