Metadata-Version: 2.1
Name: replit-storage
Version: 0.0.1a3
Summary: A library for interacting with Object Storage on Replit
Home-page: https://github.com/replit/replit-storage-python
License: ISC
Author: Repl.it
Author-email: contact@repl.it
Requires-Python: >=3.10.0,<3.11
Classifier: License :: OSI Approved
Classifier: License :: OSI Approved :: ISC License (ISCL)
Classifier: Operating System :: OS Independent
Classifier: Programming Language :: Python :: 3
Classifier: Programming Language :: Python :: 3.10
Requires-Dist: google-cloud-storage (>=2.14.0,<3.0.0)
Requires-Dist: requests (>=2.31.0,<3.0.0)
Project-URL: Repository, https://github.com/replit/replit-storage-python
